spine_engine/__init__.py
spine_engine/config.py
spine_engine/exception.py
spine_engine/jumpster.py
spine_engine/load_project_items.py
spine_engine/logger_interface.py
spine_engine/project_item_loader.py
spine_engine/spine_engine.py
spine_engine/version.py
spine_engine/execution_managers/__init__.py
spine_engine/execution_managers/conda_kernel_spec_manager.py
spine_engine/execution_managers/conda_kernel_spec_runner.py
spine_engine/execution_managers/execution_manager_base.py
spine_engine/execution_managers/kernel_execution_manager.py
spine_engine/execution_managers/persistent_execution_manager.py
spine_engine/execution_managers/process_execution_manager.py
spine_engine/execution_managers/spine_repl.jl
spine_engine/execution_managers/spine_repl.py
spine_engine/project_item/__init__.py
spine_engine/project_item/connection.py
spine_engine/project_item/executable_item_base.py
spine_engine/project_item/project_item_info.py
spine_engine/project_item/project_item_resource.py
spine_engine/project_item/project_item_specification.py
spine_engine/project_item/project_item_specification_factory.py
spine_engine/server/README.txt
spine_engine/server/__init__.py
spine_engine/server/certificate_creator.py
spine_engine/server/engine_server.py
spine_engine/server/persistent_execution_service.py
spine_engine/server/ping_service.py
spine_engine/server/project_extractor_service.py
spine_engine/server/project_remover_service.py
spine_engine/server/project_retriever_service.py
spine_engine/server/remote_execution_service.py
spine_engine/server/request.py
spine_engine/server/service_base.py
spine_engine/server/start_server.py
spine_engine/server/util/__init__.py
spine_engine/server/util/event_data_converter.py
spine_engine/server/util/server_message.py
spine_engine/server/util/zip_handler.py
spine_engine/utils/__init__.py
spine_engine/utils/command_line_arguments.py
spine_engine/utils/execution_resources.py
spine_engine/utils/helpers.py
spine_engine/utils/queue_logger.py
spine_engine-0.26.3.dist-info/licenses/COPYING
spine_engine-0.26.3.dist-info/licenses/COPYING.LESSER
spine_engine-0.26.3.dist-info/METADATA
spine_engine-0.26.3.dist-info/WHEEL
spine_engine-0.26.3.dist-info/top_level.txt
spine_engine-0.26.3.dist-info/RECORD
