Metadata-Version: 2.4
Name: spine_engine
Version: 0.26.3
Summary: A package to run Spine workflows.
Author-email: Spine Project consortium <spine_info@vtt.fi>
License: LGPL-3.0-or-later
Project-URL: Repository, https://github.com/spine-tools/spine-engine
Keywords: energy system modelling,workflow,optimisation,database
Classifier: Programming Language :: Python :: 3
Classifier: License :: OSI Approved :: GNU Lesser General Public License v3 (LGPLv3)
Classifier: Operating System :: OS Independent
Requires-Python: >=3.10
License-File: COPYING
License-File: COPYING.LESSER
Requires-Dist: networkx>2.5.1
Requires-Dist: jupyter_client>=6.0
Requires-Dist: spinedb_api>=0.36.2
Requires-Dist: pyzmq>=21.0
Requires-Dist: typing_extensions>=4.14
Dynamic: license-file
